<?xml version='1.0' encoding='UTF-8'?>
<dataset>
    <record>
        <id>1</id>
        <first_name>Anthony</first_name>
        <last_name>Le Breton</last_name>
        <email>alebreton0@storify.com</email>
        <gender>Male</gender>
        <ip_address>69.95.2.22</ip_address>
    </record>
    <record>
        <id>2</id>
        <first_name>Nicolle</first_name>
        <last_name>Brun</last_name>
        <email>nbrun1@zdnet.com</email>
        <gender>Female</gender>
        <ip_address>230.189.158.176</ip_address>
    </record>
    <record>
        <id>3</id>
        <first_name>Fields</first_name>
        <last_name>Rundle</last_name>
        <email>frundle2@com.com</email>
        <gender>Male</gender>
        <ip_address>70.128.51.197</ip_address>
    </record>
    <record>
        <id>4</id>
        <first_name>Retha</first_name>
        <last_name>O'Lennane</last_name>
        <email>rolennane3@moonfruit.com</email>
        <gender>Female</gender>
        <ip_address>75.103.215.141</ip_address>
    </record>
    <record>
        <id>5</id>
        <first_name>Raimondo</first_name>
        <last_name>Le Brom</last_name>
        <email>rlebrom4@feedburner.com</email>
        <gender>Male</gender>
        <ip_address>178.65.165.239</ip_address>
    </record>
    <record>
        <id>6</id>
        <first_name>Drusilla</first_name>
        <last_name>Cocozza</last_name>
        <email>dcocozza5@a8.net</email>
        <gender>Female</gender>
        <ip_address>164.225.204.123</ip_address>
    </record>
    <record>
        <id>7</id>
        <first_name>Aristotle</first_name>
        <last_name>Berick</last_name>
        <email>aberick6@craigslist.org</email>
        <gender>Non-binary</gender>
        <ip_address>70.32.213.213</ip_address>
    </record>
    <record>
        <id>8</id>
        <first_name>Derril</first_name>
        <last_name>Dollman</last_name>
        <email>ddollman7@xing.com</email>
        <gender>Male</gender>
        <ip_address>235.54.95.248</ip_address>
    </record>
    <record>
        <id>9</id>
        <first_name>Cicily</first_name>
        <last_name>Jagoe</last_name>
        <email>cjagoe8@marketwatch.com</email>
        <gender>Female</gender>
        <ip_address>138.106.182.101</ip_address>
    </record>
    <record>
        <id>10</id>
        <first_name>Berky</first_name>
        <last_name>Llop</last_name>
        <email>bllop9@fda.gov</email>
        <gender>Male</gender>
        <ip_address>238.221.168.172</ip_address>
    </record>
</dataset>